sse_relay_server/__init__.py
sse_relay_server/_logging.py
sse_relay_server/config.py
sse_relay_server/main.py
sse_relay_server/brokers/__init__.py
sse_relay_server/brokers/_postgres.py
sse_relay_server/brokers/_redis.py
sse_relay_server/sse_starlette/__init__.py
sse_relay_server/sse_starlette/sse.py
sse_relay_server-1.0.14.dist-info/METADATA
sse_relay_server-1.0.14.dist-info/WHEEL
sse_relay_server-1.0.14.dist-info/entry_points.txt
sse_relay_server-1.0.14.dist-info/licenses/LICENSE
sse_relay_server-1.0.14.dist-info/RECORD
