Metadata-Version: 2.1
Name: sse-relay-server
Version: 1.0.14
Summary: An SSE Relay Service: Perfect for Adding Real-Time Features to Your Django Project Without Introducing ASGI or Async Code.
Project-URL: Homepage, https://github.com/Tobi-De/sse_relay_server
Project-URL: Documentation, https://github.com/Tobi-De/sse_relay_server
Project-URL: Repository, https://github.com/Tobi-De/sse_relay_server
Author-email: Tobi DEGNON <tobidegnon@proton.me>
License: MIT License
License-File: LICENSE
Keywords: django,postgresql,python,realtime,redis
Classifier: Framework :: Django :: 4
Classifier: Framework :: Django :: 4.0
Classifier: Framework :: Django :: 4.1
Classifier: Framework :: Django :: 4.2
Classifier: Intended Audience :: Developers
Classifier: License :: OSI Approved :: MIT License
Classifier: Natural Language :: English
Classifier: Operating System :: OS Independent
Classifier: Programming Language :: Python :: 3
Classifier: Programming Language :: Python :: 3.8
Classifier: Programming Language :: Python :: 3.9
Classifier: Programming Language :: Python :: 3.10
Classifier: Programming Language :: Python :: 3.11
Classifier: Programming Language :: Python :: Implementation :: CPython
Classifier: Programming Language :: Python :: Implementation :: PyPy
Requires-Python: >=3.8
Requires-Dist: python-dotenv>=1.0.0
Requires-Dist: rich>=13.7.0
Requires-Dist: starlette>=0.31.1
Requires-Dist: structlog>=23.2.0
Requires-Dist: uvicorn[standard]>=0.23.2
Provides-Extra: postgres
Requires-Dist: psycopg[binary]>=3.1.14; extra == 'postgres'
Provides-Extra: redis
Requires-Dist: hiredis>=2.2.3; extra == 'redis'
Requires-Dist: redis>=5.0.1; extra == 'redis'
